{"key": "rin-48806", "name": "Katedralen Open  - Powered by Skylthuset", "federation": "SE", "start": "2025-03-21", "end": "2025-03-23", "source": "rin", "category": null, "matches": [{"className": "Herr C", "round": "Herrar C", "court": "Bana 12", "status": "final", "teams": [{"name": "Johan Andersson / Claudio Carvajal", "players": [{"name": "Johan Andersson", "country": "se"}, {"name": "Claudio Carvajal", "country": "se"}]}, {"name": "Marcus Lindström / William Lenz", "players": [{"name": "Marcus Lindström", "country": "se"}, {"name": "William Lenz", "country": "se"}]}], "score": {"sets": [["6", "2"], ["6", "0"]], "winner": 0}}, {"className": "Herr C", "round": "Herrar C", "court": "Bana 13", "status": "final", "teams": [{"name": "Andreas Lindström / Jesper Andersson", "players": [{"name": "Andreas Lindström", "country": "se"}, {"name": "Jesper Andersson", "country": "se"}]}, {"name": "Konrad Jönsson / Otto Carlsson", "players": [{"name": "Konrad Jönsson", "country": "se"}, {"name": "Otto Carlsson", "country": "se"}]}], "score": {"sets": [["6", "3"], ["6", "4"]], "winner": 0}}, {"className": "Herr C", "round": "Herrar C", "court": "Bana 2", "status": "final", "teams": [{"name": "Melwin Svensson / Alvar Stenfeldt", "players": [{"name": "Melwin Svensson", "country": "se"}, {"name": "Alvar Stenfeldt", "country": "se"}]}, {"name": "Daniel Eliasson / Oliver Parsons", "players": [{"name": "Daniel Eliasson", "country": "se"}, {"name": "Oliver Parsons", "country": "se"}]}], "score": {"sets": [["6", "4"], ["6", "4"]], "winner": 0}}, {"className": "Herr C", "round": "Herrar C", "court": "Bana 3", "status": "final", "teams": [{"name": "Alexander Olsson / Erik Andersson", "players": [{"name": "Alexander Olsson", "country": "se"}, {"name": "Erik Andersson", "country": "se"}]}, {"name": "Fredrik Ho / Oskar Persson", "players": [{"name": "Fredrik Ho", "country": "se"}, {"name": "Oskar Persson", "country": "se"}]}], "score": {"sets": [["6", "1"], ["6", "7"], ["7", "6"]], "winner": 0}}, {"className": "Herr C", "round": "Herrar C", "court": "Bana 4", "status": "final", "teams": [{"name": "Patrik Henriksen / Tobias Brants", "players": [{"name": "Patrik Henriksen", "country": "se"}, {"name": "Tobias Brants", "country": "se"}]}, {"name": "André Johansson / Robin Johansson", "players": [{"name": "André Johansson", "country": "se"}, {"name": "Robin Johansson", "country": "se"}]}], "score": {"sets": [["6", "1"], ["4", "6"], ["1", "0"]], "winner": 0}}, {"className": "Herr C", "round": "Herrar C", "court": "Bana 10", "status": "final", "teams": [{"name": "Magnus Wahlström / Jörgen Eriksson", "players": [{"name": "Magnus Wahlström", "country": "se"}, {"name": "Jörgen Eriksson", "country": "se"}]}, {"name": "Tim Apell / Kevin Long", "players": [{"name": "Tim Apell", "country": "se"}, {"name": "Kevin Long", "country": "se"}]}], "score": {"sets": [["6", "1"], ["6", "1"]], "winner": 0}}, {"className": "Herr C", "round": "Herrar C", "court": "Bana 11", "status": "final", "teams": [{"name": "Jonas Lindholm / Benny Gustafsson", "players": [{"name": "Jonas Lindholm", "country": "se"}, {"name": "Benny Gustafsson", "country": "se"}]}, {"name": "Stefan Vanemo / Christer Kjellberg", "players": [{"name": "Stefan Vanemo", "country": "se"}, {"name": "Christer Kjellberg", "country": "se"}]}], "score": {"sets": [["6", "2"], ["6", "4"]], "winner": 0}}, {"className": "Herr C", "round": "Herrar C", "court": "Bana 1", "status": "final", "teams": [{"name": "Sixten Ahlquist / Waldemar Oddshammar", "players": [{"name": "Sixten Ahlquist", "country": "se"}, {"name": "Waldemar Oddshammar", "country": "se"}]}, {"name": "Jacob Celind / Julius Tunmats", "players": [{"name": "Jacob Celind", "country": "se"}, {"name": "Julius Tunmats", "country": "se"}]}], "score": {"sets": [["6", "1"], ["6", "1"]], "winner": 0}}, {"className": "Herr C", "round": "Herrar C", "court": "Bana 5", "status": "final", "teams": [{"name": "Niklas Johansson / Christopher Lindell", "players": [{"name": "Niklas Johansson", "country": "se"}, {"name": "Christopher Lindell", "country": "se"}]}, {"name": "Markus Ekstrand / Simon Lindell", "players": [{"name": "Markus Ekstrand", "country": "se"}, {"name": "Simon Lindell", "country": "se"}]}], "score": {"sets": [["6", "4"], ["6", "4"]], "winner": 0}}, {"className": "Herr C", "round": "Herrar C", "court": "Bana 6 (centercourt)", "status": "final", "teams": [{"name": "M. Faour / Oliver Ponné", "players": [{"name": "M. Faour", "country": "ps"}, {"name": "Oliver Ponné", "country": "se"}]}, {"name": "Joakim Sjunnesson / Thomas Eklöv", "players": [{"name": "Joakim Sjunnesson", "country": "se"}, {"name": "Thomas Eklöv", "country": "se"}]}], "score": {"sets": [["6", "2"], ["6", "2"]], "winner": 0}}, {"className": "Herr A", "round": "Herrar A", "court": "Bana 12", "status": "final", "teams": [{"name": "Emil Lilleøre / Nicolai Tranberg Ferrigno", "players": [{"name": "Emil Lilleøre", "country": "dk"}, {"name": "Nicolai Tranberg Ferrigno", "country": "dk"}]}, {"name": "Joel Svensson / Per Ågren", "players": [{"name": "Joel Svensson", "country": "se"}, {"name": "Per Ågren", "country": "se"}]}], "score": {"sets": [], "winner": null}}, {"className": "Herr C", "round": "Herrar C", "court": "Bana 10", "status": "final", "teams": [{"name": "Claes Engström / Markus Hedin", "players": [{"name": "Claes Engström", "country": "se"}, {"name": "Markus Hedin", "country": "se"}]}, {"name": "Felix Erlanson / Ronny Norell", "players": [{"name": "Felix Erlanson", "country": "se"}, {"name": "Ronny Norell", "country": "se"}]}], "score": {"sets": [["6", "2"], ["6", "4"]], "winner": 0}}, {"className": "Herr C", "round": "Herrar C", "court": "Bana 6 (centercourt)", "status": "final", "teams": [{"name": "Tim Toth / Gustav Berg", "players": [{"name": "Tim Toth", "country": "se"}, {"name": "Gustav Berg", "country": "se"}]}, {"name": "Ludvig Jerpö / Gustaf Kull", "players": [{"name": "Ludvig Jerpö", "country": "se"}, {"name": "Gustaf Kull", "country": "se"}]}], "score": {"sets": [["6", "4"], ["7", "5"]], "winner": 0}}, {"className": "Herr C", "round": "Herrar C", "court": "Bana 5", "status": "final", "teams": [{"name": "Erik Isaksson / Björn Santesson", "players": [{"name": "Erik Isaksson", "country": "se"}, {"name": "Björn Santesson", "country": "se"}]}, {"name": "Alfred Keller / Max Lessmann", "players": [{"name": "Alfred Keller", "country": "se"}, {"name": "Max Lessmann", "country": "se"}]}], "score": {"sets": [["6", "7"], ["6", "3"], ["1", "0"]], "winner": 0}}, {"className": "Herr C", "round": "Herrar C", "court": "Bana 11", "status": "final", "teams": [{"name": "Isac Magnusson / Marcus Persson", "players": [{"name": "Isac Magnusson", "country": "se"}, {"name": "Marcus Persson", "country": "se"}]}, {"name": "Oliver Svenningsson / Melker Turunen", "players": [{"name": "Oliver Svenningsson", "country": "se"}, {"name": "Melker Turunen", "country": "se"}]}], "score": {"sets": [["6", "3"], ["2", "6"], ["1", "0"]], "winner": 0}}, {"className": "Herr C", "round": "Herrar C", "court": "Bana 4", "status": "final", "teams": [{"name": "Thomas Dalebring / Herman Nordin", "players": [{"name": "Thomas Dalebring", "country": "se"}, {"name": "Herman Nordin", "country": "se"}]}, {"name": "Tobias Sjölin / Rikard Brogårde", "players": [{"name": "Tobias Sjölin", "country": "se"}, {"name": "Rikard Brogårde", "country": "se"}]}], "score": {"sets": [["6", "2"], ["6", "3"]], "winner": 0}}, {"className": "Herr C", "round": "Herrar C", "court": "Bana 1", "status": "final", "teams": [{"name": "Robin Dristig / Christopher Åberg", "players": [{"name": "Robin Dristig", "country": "se"}, {"name": "Christopher Åberg", "country": "se"}]}, {"name": "Zebastian Jönsson / Marcus Fernlid", "players": [{"name": "Zebastian Jönsson", "country": "se"}, {"name": "Marcus Fernlid", "country": "se"}]}], "score": {"sets": [["7", "5"], ["7", "6"]], "winner": 0}}, {"className": "Dam A", "round": "Damer A", "court": "Bana 2", "status": "final", "teams": [{"name": "Maja Åberg / Elma Misanovic", "players": [{"name": "Maja Åberg", "country": "se"}, {"name": "Elma Misanovic", "country": "se"}]}, {"name": "Asta Renemark / Julia Gustafsson", "players": [{"name": "Asta Renemark", "country": "se"}, {"name": "Julia Gustafsson", "country": "se"}]}], "score": {"sets": [["7", "5"], ["7", "5"]], "winner": 0}}, {"className": "Dam A", "round": "Damer A", "court": "Bana 6 (centercourt)", "status": "final", "teams": [{"name": "Carla Barciela / Tea Hylander", "players": [{"name": "Carla Barciela", "country": "es"}, {"name": "Tea Hylander", "country": "se"}]}, {"name": "Linn Kallio / Jennifer Pierre", "players": [{"name": "Linn Kallio", "country": "se"}, {"name": "Jennifer Pierre", "country": "se"}]}], "score": {"sets": [["6", "4"], ["6", "2"]], "winner": 0}}, {"className": "Dam A", "round": "Damer A", "court": "Bana 4", "status": "final", "teams": [{"name": "Cornelia Lister Haglind / Lisa Andersson", "players": [{"name": "Cornelia Lister Haglind", "country": "se"}, {"name": "Lisa Andersson", "country": "se"}]}, {"name": "Elsa Blom / Emma Lindberg", "players": [{"name": "Elsa Blom", "country": "se"}, {"name": "Emma Lindberg", "country": "se"}]}], "score": {"sets": [["6", "3"], ["7", "6"]], "winner": 0}}, {"className": "Dam A", "round": "Damer A", "court": "Bana 10", "status": "final", "teams": [{"name": "Baharak Soleymani / Maria García-Rasmussen", "players": [{"name": "Baharak Soleymani", "country": "se"}, {"name": "Maria García-Rasmussen", "country": "dk"}]}, {"name": "Linnéa Skymberg / Filippa Vial", "players": [{"name": "Linnéa Skymberg", "country": "se"}, {"name": "Filippa Vial", "country": "se"}]}], "score": {"sets": [["6", "4"], ["6", "0"]], "winner": 0}}, {"className": "Dam A", "round": "Damer A", "court": "Bana 3", "status": "final", "teams": [{"name": "Eliza Bosson / Laura  Gomez", "players": [{"name": "Eliza Bosson", "country": "se"}, {"name": "Laura  Gomez", "country": "es"}]}, {"name": "Zoe Andersson / Silje Kjaergaard", "players": [{"name": "Zoe Andersson", "country": "se"}, {"name": "Silje Kjaergaard", "country": "se"}]}], "score": {"sets": [], "winner": null}}, {"className": "Dam A", "round": "Damer A", "court": "Bana 1", "status": "final", "teams": [{"name": "Anna Jonzon / Simone Alipieva", "players": [{"name": "Anna Jonzon", "country": "se"}, {"name": "Simone Alipieva", "country": "dk"}]}, {"name": "Ella Ho / Anna Riisgaard", "players": [{"name": "Ella Ho", "country": "se"}, {"name": "Anna Riisgaard", "country": "dk"}]}], "score": {"sets": [["6", "1"], ["6", "3"]], "winner": 0}}, {"className": "Dam B", "round": "Damer B", "court": "Bana 5", "status": "final", "teams": [{"name": "Frida Bengtsson / Linda Mernsten", "players": [{"name": "Frida Bengtsson", "country": "se"}, {"name": "Linda Mernsten", "country": "se"}]}, {"name": "Emily Shabacker / Sophia Hagwell", "players": [{"name": "Emily Shabacker", "country": "se"}, {"name": "Sophia Hagwell", "country": "se"}]}], "score": {"sets": [], "winner": null}}, {"className": "Herr C", "round": "Herrar C", "court": "Bana 15", "status": "final", "teams": [{"name": "Konrad Jönsson / Otto Carlsson", "players": [{"name": "Konrad Jönsson", "country": "se"}, {"name": "Otto Carlsson", "country": "se"}]}, {"name": "Marcus Lindström / William Lenz", "players": [{"name": "Marcus Lindström", "country": "se"}, {"name": "William Lenz", "country": "se"}]}], "score": {"sets": [["6", "3"], ["6", "0"]], "winner": 0}}, {"className": "Herr C", "round": "Herrar C", "court": "Bana 14", "status": "final", "teams": [{"name": "Daniel Eliasson / Oliver Parsons", "players": [{"name": "Daniel Eliasson", "country": "se"}, {"name": "Oliver Parsons", "country": "se"}]}, {"name": "Fredrik Ho / Oskar Persson", "players": [{"name": "Fredrik Ho", "country": "se"}, {"name": "Oskar Persson", "country": "se"}]}], "score": {"sets": [["7", "5"], ["4", "6"], ["1", "0"]], "winner": 0}}, {"className": "Herr C", "round": "Herrar C", "court": "Bana 13", "status": "final", "teams": [{"name": "Tim Apell / Kevin Long", "players": [{"name": "Tim Apell", "country": "se"}, {"name": "Kevin Long", "country": "se"}]}, {"name": "André Johansson / Robin Johansson", "players": [{"name": "André Johansson", "country": "se"}, {"name": "Robin Johansson", "country": "se"}]}], "score": {"sets": [["6", "3"], ["6", "4"]], "winner": 0}}, {"className": "Herr C", "round": "Herrar C", "court": "Bana 17", "status": "final", "teams": [{"name": "Stefan Vanemo / Christer Kjellberg", "players": [{"name": "Stefan Vanemo", "country": "se"}, {"name": "Christer Kjellberg", "country": "se"}]}, {"name": "Jacob Celind / Julius Tunmats", "players": [{"name": "Jacob Celind", "country": "se"}, {"name": "Julius Tunmats", "country": "se"}]}], "score": {"sets": [["6", "3"], ["5", "4"]], "winner": 0}}, {"className": "Herr C", "round": "Herrar C", "court": "Bana 16", "status": "final", "teams": [{"name": "Felix Erlanson / Ronny Norell", "players": [{"name": "Felix Erlanson", "country": "se"}, {"name": "Ronny Norell", "country": "se"}]}, {"name": "Ludvig Jerpö / Gustaf Kull", "players": [{"name": "Ludvig Jerpö", "country": "se"}, {"name": "Gustaf Kull", "country": "se"}]}], "score": {"sets": [["6", "3"], ["6", "1"]], "winner": 0}}, {"className": "Herr C", "round": "Herrar C", "court": "Bana 12", "status": "final", "teams": [{"name": "Zebastian Jönsson / Marcus Fernlid", "players": [{"name": "Zebastian Jönsson", "country": "se"}, {"name": "Marcus Fernlid", "country": "se"}]}, {"name": "Alfred Keller / Max Lessmann", "players": [{"name": "Alfred Keller", "country": "se"}, {"name": "Max Lessmann", "country": "se"}]}], "score": {"sets": [["6", "4"], ["6", "1"]], "winner": 0}}, {"className": "Herr C", "round": "Herrar C", "court": "Bana 11", "status": "final", "teams": [{"name": "Tobias Sjölin / Rikard Brogårde", "players": [{"name": "Tobias Sjölin", "country": "se"}, {"name": "Rikard Brogårde", "country": "se"}]}, {"name": "Oliver Svenningsson / Melker Turunen", "players": [{"name": "Oliver Svenningsson", "country": "se"}, {"name": "Melker Turunen", "country": "se"}]}], "score": {"sets": [["6", "2"], ["6", "4"]], "winner": 0}}, {"className": "Dam A", "round": "Damer A", "court": "Bana 11", "status": "final", "teams": [{"name": "Linnéa Skymberg / Filippa Vial", "players": [{"name": "Linnéa Skymberg", "country": "se"}, {"name": "Filippa Vial", "country": "se"}]}, {"name": "Zoe Andersson / Silje Kjaergaard", "players": [{"name": "Zoe Andersson", "country": "se"}, {"name": "Silje Kjaergaard", "country": "se"}]}], "score": {"sets": [], "winner": null}}, {"className": "Herr A", "round": "Herrar A", "court": "Bana 1", "status": "final", "teams": [{"name": "Albin Olsson / Douglas Rutgersson", "players": [{"name": "Albin Olsson", "country": "se"}, {"name": "Douglas Rutgersson", "country": "se"}]}, {"name": "Emil Lilleøre / Nicolai Tranberg Ferrigno", "players": [{"name": "Emil Lilleøre", "country": "dk"}, {"name": "Nicolai Tranberg Ferrigno", "country": "dk"}]}], "score": {"sets": [["6", "2"], ["6", "4"]], "winner": 0}}, {"className": "Herr A", "round": "Herrar A", "court": "Bana 5", "status": "final", "teams": [{"name": "Måns Stapel / Anton Mickelsson", "players": [{"name": "Måns Stapel", "country": "se"}, {"name": "Anton Mickelsson", "country": "se"}]}, {"name": "Linus Isaksson / Erik Nordström", "players": [{"name": "Linus Isaksson", "country": "se"}, {"name": "Erik Nordström", "country": "se"}]}], "score": {"sets": [["6", "2"], ["6", "2"]], "winner": 0}}, {"className": "Herr A", "round": "Herrar A", "court": "Bana 10", "status": "final", "teams": [{"name": "Ebbe Badersten / Pablo Sanchez Vicente", "players": [{"name": "Ebbe Badersten", "country": "se"}, {"name": "Pablo Sanchez Vicente", "country": "es"}]}, {"name": "Willy Tiger Släryd / Huysveld Isaac", "players": [{"name": "Willy Tiger Släryd", "country": "se"}, {"name": "Huysveld Isaac", "country": "be"}]}], "score": {"sets": [["7", "6"], ["6", "3"]], "winner": 0}}, {"className": "Herr A", "round": "Herrar A", "court": "Bana 4", "status": "final", "teams": [{"name": "Simon Yitbarek / Adam Axelsson", "players": [{"name": "Simon Yitbarek", "country": "se"}, {"name": "Adam Axelsson", "country": "se"}]}, {"name": "Oliver Hodos / Felix Bengtsson", "players": [{"name": "Oliver Hodos", "country": "se"}, {"name": "Felix Bengtsson", "country": "se"}]}], "score": {"sets": [["6", "4"], ["6", "4"]], "winner": 0}}, {"className": "Herr A", "round": "Herrar A", "court": "Bana 3", "status": "final", "teams": [{"name": "Adam Svensson / Marcus Månsson", "players": [{"name": "Adam Svensson", "country": "se"}, {"name": "Marcus Månsson", "country": "se"}]}, {"name": "Alfons Lopez / Adam Ottosson", "players": [{"name": "Alfons Lopez", "country": "se"}, {"name": "Adam Ottosson", "country": "se"}]}], "score": {"sets": [], "winner": null}}, {"className": "Herr A", "round": "Herrar A", "court": "Bana 2", "status": "final", "teams": [{"name": "Carl Knutsson / Oskar Govik", "players": [{"name": "Carl Knutsson", "country": "se"}, {"name": "Oskar Govik", "country": "se"}]}, {"name": "Mac Grossmann / Adam Gustafsson", "players": [{"name": "Mac Grossmann", "country": "sk"}, {"name": "Adam Gustafsson", "country": "se"}]}], "score": {"sets": [["6", "2"], ["6", "4"]], "winner": 0}}, {"className": "Herr A", "round": "Herrar A", "court": "Bana 6 (centercourt)", "status": "final", "teams": [{"name": "Daniel Appelgren / Linus Frost", "players": [{"name": "Daniel Appelgren", "country": "se"}, {"name": "Linus Frost", "country": "se"}]}, {"name": "Malte Badersten / Juan Figueroa Ayala", "players": [{"name": "Malte Badersten", "country": "se"}, {"name": "Juan Figueroa Ayala", "country": "es"}]}], "score": {"sets": [["6", "4"], ["6", "1"]], "winner": 0}}, {"className": "Herr B", "round": "Herrar B", "court": "Bana 15", "status": "final", "teams": [{"name": "Noel Wändemark / Oskar Elmevik", "players": [{"name": "Noel Wändemark", "country": "se"}, {"name": "Oskar Elmevik", "country": "se"}]}, {"name": "Kristoffer Mohell Manneh / Jeronimo R Lacno", "players": [{"name": "Kristoffer Mohell Manneh", "country": "gm"}, {"name": "Jeronimo R Lacno", "country": "ph"}]}], "score": {"sets": [["6", "0"], ["7", "6"]], "winner": 0}}, {"className": "Herr B", "round": "Herrar B", "court": "Bana 14", "status": "final", "teams": [{"name": "Malte Rasmusson / Hugo Henrysson", "players": [{"name": "Malte Rasmusson", "country": "se"}, {"name": "Hugo Henrysson", "country": "se"}]}, {"name": "Fredrik Ifvarsson / Fredrik Grundström", "players": [{"name": "Fredrik Ifvarsson", "country": "se"}, {"name": "Fredrik Grundström", "country": "se"}]}], "score": {"sets": [["6", "2"], ["6", "4"]], "winner": 0}}, {"className": "Herr B", "round": "Herrar B", "court": "Bana 13", "status": "final", "teams": [{"name": "William Johansson / Alberto Gonzalez", "players": [{"name": "William Johansson", "country": "se"}, {"name": "Alberto Gonzalez", "country": "es"}]}, {"name": "Carl-Johan Bergensjö / Peter Calonne", "players": [{"name": "Carl-Johan Bergensjö", "country": "se"}, {"name": "Peter Calonne", "country": "se"}]}], "score": {"sets": [["6", "2"], ["6", "2"]], "winner": 0}}, {"className": "Herr B", "round": "Herrar B", "court": "Bana 12", "status": "final", "teams": [{"name": "Elliot Haväng / Linus Andersson", "players": [{"name": "Elliot Haväng", "country": "se"}, {"name": "Linus Andersson", "country": "se"}]}, {"name": "Anders Erikson / Anton Wittgren", "players": [{"name": "Anders Erikson", "country": "se"}, {"name": "Anton Wittgren", "country": "se"}]}], "score": {"sets": [["6", "2"], ["6", "1"]], "winner": 0}}, {"className": "Herr C", "round": "Herrar C", "court": "Bana 17", "status": "final", "teams": [{"name": "Markus Ekstrand / Simon Lindell", "players": [{"name": "Markus Ekstrand", "country": "se"}, {"name": "Simon Lindell", "country": "se"}]}, {"name": "Joakim Sjunnesson / Thomas Eklöv", "players": [{"name": "Joakim Sjunnesson", "country": "se"}, {"name": "Thomas Eklöv", "country": "se"}]}], "score": {"sets": [], "winner": null}}, {"className": "Herr A", "round": "Herrar A", "court": "Bana 6 (centercourt)", "status": "final", "teams": [{"name": "Oscar Sebber / Alex Loughlan", "players": [{"name": "Oscar Sebber", "country": "dk"}, {"name": "Alex Loughlan", "country": "gb"}]}, {"name": "Gustav Eriksson / Christoffer Persson", "players": [{"name": "Gustav Eriksson", "country": "se"}, {"name": "Christoffer Persson", "country": "se"}]}], "score": {"sets": [["6", "2"], ["6", "4"]], "winner": 0}}, {"className": "Herr C", "round": "Herrar C", "court": "Bana 16", "status": "final", "teams": [{"name": "M. Faour / Oliver Ponné", "players": [{"name": "M. Faour", "country": "ps"}, {"name": "Oliver Ponné", "country": "se"}]}, {"name": "Niklas Johansson / Christopher Lindell", "players": [{"name": "Niklas Johansson", "country": "se"}, {"name": "Christopher Lindell", "country": "se"}]}], "score": {"sets": [["7", "6"], ["6", "4"]], "winner": 0}}, {"className": "Herr C", "round": "Herrar C", "court": "Bana 13", "status": "final", "teams": [{"name": "Thomas Dalebring / Herman Nordin", "players": [{"name": "Thomas Dalebring", "country": "se"}, {"name": "Herman Nordin", "country": "se"}]}, {"name": "Isac Magnusson / Marcus Persson", "players": [{"name": "Isac Magnusson", "country": "se"}, {"name": "Marcus Persson", "country": "se"}]}], "score": {"sets": [["6", "2"], ["7", "5"]], "winner": 0}}, {"className": "Herr C", "round": "Herrar C", "court": "Bana 15", "status": "final", "teams": [{"name": "Robin Dristig / Christopher Åberg", "players": [{"name": "Robin Dristig", "country": "se"}, {"name": "Christopher Åberg", "country": "se"}]}, {"name": "Erik Isaksson / Björn Santesson", "players": [{"name": "Erik Isaksson", "country": "se"}, {"name": "Björn Santesson", "country": "se"}]}], "score": {"sets": [["6", "3"], ["6", "4"]], "winner": 0}}, {"className": "Herr C", "round": "Herrar C", "court": "Bana 14", "status": "final", "teams": [{"name": "Andreas Lindström / Jesper Andersson", "players": [{"name": "Andreas Lindström", "country": "se"}, {"name": "Jesper Andersson", "country": "se"}]}, {"name": "Johan Andersson / Claudio Carvajal", "players": [{"name": "Johan Andersson", "country": "se"}, {"name": "Claudio Carvajal", "country": "se"}]}], "score": {"sets": [["6", "3"], ["6", "4"]], "winner": 0}}, {"className": "Herr C", "round": "Herrar C", "court": "Bana 10", "status": "final", "teams": [{"name": "Alexander Olsson / Erik Andersson", "players": [{"name": "Alexander Olsson", "country": "se"}, {"name": "Erik Andersson", "country": "se"}]}, {"name": "Melwin Svensson / Alvar Stenfeldt", "players": [{"name": "Melwin Svensson", "country": "se"}, {"name": "Alvar Stenfeldt", "country": "se"}]}], "score": {"sets": [["6", "4"], ["7", "5"]], "winner": 0}}, {"className": "Herr C", "round": "Herrar C", "court": "Bana 12", "status": "final", "teams": [{"name": "Magnus Wahlström / Jörgen Eriksson", "players": [{"name": "Magnus Wahlström", "country": "se"}, {"name": "Jörgen Eriksson", "country": "se"}]}, {"name": "Patrik Henriksen / Tobias Brants", "players": [{"name": "Patrik Henriksen", "country": "se"}, {"name": "Tobias Brants", "country": "se"}]}], "score": {"sets": [["6", "3"], ["6", "1"]], "winner": 0}}, {"className": "Herr C", "round": "Herrar C", "court": "Bana 11", "status": "final", "teams": [{"name": "Sixten Ahlquist / Waldemar Oddshammar", "players": [{"name": "Sixten Ahlquist", "country": "se"}, {"name": "Waldemar Oddshammar", "country": "se"}]}, {"name": "Jonas Lindholm / Benny Gustafsson", "players": [{"name": "Jonas Lindholm", "country": "se"}, {"name": "Benny Gustafsson", "country": "se"}]}], "score": {"sets": [["6", "1"], ["6", "4"]], "winner": 0}}, {"className": "Dam C", "round": "Damer C", "court": "Bana 5", "status": "final", "teams": [{"name": "Lola Teikari / Alice Andersson", "players": [{"name": "Lola Teikari", "country": "se"}, {"name": "Alice Andersson", "country": "se"}]}, {"name": "Evelina Norell / Jessica Andersson", "players": [{"name": "Evelina Norell", "country": "se"}, {"name": "Jessica Andersson", "country": "se"}]}], "score": {"sets": [["7", "6"], ["6", "2"]], "winner": 0}}, {"className": "Dam C", "round": "Damer C", "court": "Bana 4", "status": "final", "teams": [{"name": "Louise Malmström / Sofie Linderholm", "players": [{"name": "Louise Malmström", "country": "se"}, {"name": "Sofie Linderholm", "country": "se"}]}, {"name": "Malin Jungåker / Ebba Jolde", "players": [{"name": "Malin Jungåker", "country": "se"}, {"name": "Ebba Jolde", "country": "se"}]}], "score": {"sets": [["6", "4"], ["6", "1"]], "winner": 0}}, {"className": "Dam C", "round": "Damer C", "court": "Bana 3", "status": "final", "teams": [{"name": "Mikaela Åkerman / Linnéa Freiding", "players": [{"name": "Mikaela Åkerman", "country": "se"}, {"name": "Linnéa Freiding", "country": "se"}]}, {"name": "Tilda Mahrberg / Maja Jansson", "players": [{"name": "Tilda Mahrberg", "country": "se"}, {"name": "Maja Jansson", "country": "se"}]}], "score": {"sets": [["6", "1"], ["7", "5"]], "winner": 0}}, {"className": "Dam C", "round": "Damer C", "court": "Bana 2", "status": "final", "teams": [{"name": "Ewa Jönsson / Louise Falkengren", "players": [{"name": "Ewa Jönsson", "country": "se"}, {"name": "Louise Falkengren", "country": "se"}]}, {"name": "Malin Axelsson / Frida Glimstål", "players": [{"name": "Malin Axelsson", "country": "se"}, {"name": "Frida Glimstål", "country": "se"}]}], "score": {"sets": [["6", "3"], ["6", "4"]], "winner": 0}}, {"className": "Dam C", "round": "Damer C", "court": "Bana 1", "status": "final", "teams": [{"name": "Stella Svensson / Ella Nordström", "players": [{"name": "Stella Svensson", "country": "se"}, {"name": "Ella Nordström", "country": "se"}]}, {"name": "Tina Johansson / Emma Mauritzon", "players": [{"name": "Tina Johansson", "country": "se"}, {"name": "Emma Mauritzon", "country": "se"}]}], "score": {"sets": [["6", "3"], ["6", "2"]], "winner": 0}}, {"className": "Dam C", "round": "Damer C", "court": "Bana 17", "status": "final", "teams": [{"name": "Mia Glimbrand / Sofia Grönvall", "players": [{"name": "Mia Glimbrand", "country": "se"}, {"name": "Sofia Grönvall", "country": "se"}]}, {"name": "Heli Hämäläinen / Caroline Blomsten", "players": [{"name": "Heli Hämäläinen", "country": "se"}, {"name": "Caroline Blomsten", "country": "se"}]}], "score": {"sets": [["6", "3"], ["4", "6"], ["1", "0"]], "winner": 0}}, {"className": "Dam A", "round": "Damer A", "court": "Bana 14", "status": "final", "teams": [{"name": "Ella Ho / Anna Riisgaard", "players": [{"name": "Ella Ho", "country": "se"}, {"name": "Anna Riisgaard", "country": "dk"}]}, {"name": "Linnéa Skymberg / Filippa Vial", "players": [{"name": "Linnéa Skymberg", "country": "se"}, {"name": "Filippa Vial", "country": "se"}]}], "score": {"sets": [["1", "6"], ["7", "5"], ["1", "0"]], "winner": 0}}, {"className": "Dam A", "round": "Damer A", "court": "Bana 6 (centercourt)", "status": "final", "teams": [{"name": "Linnea Björk / Amanda Girdo", "players": [{"name": "Linnea Björk", "country": "se"}, {"name": "Amanda Girdo", "country": "se"}]}, {"name": "Anna Jonzon / Simone Alipieva", "players": [{"name": "Anna Jonzon", "country": "se"}, {"name": "Simone Alipieva", "country": "dk"}]}], "score": {"sets": [["6", "3"], ["6", "3"]], "winner": 0}}, {"className": "Dam B", "round": "Damer B", "court": "Bana 4", "status": "final", "teams": [{"name": "Jonna Opitz / Anna-Karin Svensson", "players": [{"name": "Jonna Opitz", "country": "se"}, {"name": "Anna-Karin Svensson", "country": "se"}]}, {"name": "Eva Berg / Birgitta Bengtson", "players": [{"name": "Eva Berg", "country": "se"}, {"name": "Birgitta Bengtson", "country": "se"}]}], "score": {"sets": [["6", "1"], ["6", "0"]], "winner": 0}}, {"className": "Dam B", "round": "Damer B", "court": "Bana 3", "status": "final", "teams": [{"name": "Greta Åberg / Emilia Andreadis", "players": [{"name": "Greta Åberg", "country": "se"}, {"name": "Emilia Andreadis", "country": "se"}]}, {"name": "Johanna Ejdelind / Caroline Molander", "players": [{"name": "Johanna Ejdelind", "country": "se"}, {"name": "Caroline Molander", "country": "se"}]}], "score": {"sets": [["6", "4"], ["0", "6"], ["1", "0"]], "winner": 0}}, {"className": "Dam B", "round": "Damer B", "court": "Bana 1", "status": "final", "teams": [{"name": "Selma Killman / Ann Roslund", "players": [{"name": "Selma Killman", "country": "se"}, {"name": "Ann Roslund", "country": "se"}]}, {"name": "Ann-Charlotte Granqvist / Ulrika de Paulis", "players": [{"name": "Ann-Charlotte Granqvist", "country": "se"}, {"name": "Ulrika de Paulis", "country": "se"}]}], "score": {"sets": [["6", "0"], ["6", "4"]], "winner": 0}}, {"className": "Herr A", "round": "Herrar A", "court": "Bana 15", "status": "final", "teams": [{"name": "Emil Lilleøre / Nicolai Tranberg Ferrigno", "players": [{"name": "Emil Lilleøre", "country": "dk"}, {"name": "Nicolai Tranberg Ferrigno", "country": "dk"}]}, {"name": "Linus Isaksson / Erik Nordström", "players": [{"name": "Linus Isaksson", "country": "se"}, {"name": "Erik Nordström", "country": "se"}]}], "score": {"sets": [["6", "4"], ["6", "2"]], "winner": 0}}, {"className": "Herr B", "round": "Herrar B", "court": "Bana 16", "status": "final", "teams": [{"name": "Anders Erikson / Anton Wittgren", "players": [{"name": "Anders Erikson", "country": "se"}, {"name": "Anton Wittgren", "country": "se"}]}, {"name": "Carl-Johan Bergensjö / Peter Calonne", "players": [{"name": "Carl-Johan Bergensjö", "country": "se"}, {"name": "Peter Calonne", "country": "se"}]}], "score": {"sets": [["7", "5"], ["6", "3"]], "winner": 0}}, {"className": "Herr C", "round": "Herrar C", "court": "Bana 17", "status": "final", "teams": [{"name": "Daniel Eliasson / Oliver Parsons", "players": [{"name": "Daniel Eliasson", "country": "se"}, {"name": "Oliver Parsons", "country": "se"}]}, {"name": "Konrad Jönsson / Otto Carlsson", "players": [{"name": "Konrad Jönsson", "country": "se"}, {"name": "Otto Carlsson", "country": "se"}]}], "score": {"sets": [["7", "5"], ["6", "3"]], "winner": 0}}, {"className": "Herr C", "round": "Herrar C", "court": "Bana 11", "status": "final", "teams": [{"name": "Tim Apell / Kevin Long", "players": [{"name": "Tim Apell", "country": "se"}, {"name": "Kevin Long", "country": "se"}]}, {"name": "Stefan Vanemo / Christer Kjellberg", "players": [{"name": "Stefan Vanemo", "country": "se"}, {"name": "Christer Kjellberg", "country": "se"}]}], "score": {"sets": [["7", "6"], ["6", "1"]], "winner": 0}}, {"className": "Herr C", "round": "Herrar C", "court": "Bana 12", "status": "final", "teams": [{"name": "Felix Erlanson / Ronny Norell", "players": [{"name": "Felix Erlanson", "country": "se"}, {"name": "Ronny Norell", "country": "se"}]}, {"name": "Zebastian Jönsson / Marcus Fernlid", "players": [{"name": "Zebastian Jönsson", "country": "se"}, {"name": "Marcus Fernlid", "country": "se"}]}], "score": {"sets": [["6", "0"], ["6", "2"]], "winner": 0}}, {"className": "Herr C", "round": "Herrar C", "court": "Bana 10", "status": "final", "teams": [{"name": "Claes Engström / Markus Hedin", "players": [{"name": "Claes Engström", "country": "se"}, {"name": "Markus Hedin", "country": "se"}]}, {"name": "Tim Toth / Gustav Berg", "players": [{"name": "Tim Toth", "country": "se"}, {"name": "Gustav Berg", "country": "se"}]}], "score": {"sets": [["6", "4"], ["6", "3"]], "winner": 0}}, {"className": "Dam C", "round": "Damer C", "court": "Bana 13", "status": "final", "teams": [{"name": "Jaqueline Delang / Josefin Lindgren", "players": [{"name": "Jaqueline Delang", "country": "se"}, {"name": "Josefin Lindgren", "country": "se"}]}, {"name": "Angela Dron / Cecilia Cederek", "players": [{"name": "Angela Dron", "country": "au"}, {"name": "Cecilia Cederek", "country": "se"}]}], "score": {"sets": [["6", "3"], ["6", "1"]], "winner": 0}}, {"className": "Dam A", "round": "Damer A", "court": "Bana 1", "status": "final", "teams": [{"name": "Elsa Blom / Emma Lindberg", "players": [{"name": "Elsa Blom", "country": "se"}, {"name": "Emma Lindberg", "country": "se"}]}, {"name": "Linn Kallio / Jennifer Pierre", "players": [{"name": "Linn Kallio", "country": "se"}, {"name": "Jennifer Pierre", "country": "se"}]}], "score": {"sets": [["6", "2"], ["4", "6"], ["6", "2"]], "winner": 0}}, {"className": "Dam A", "round": "Damer A", "court": "Bana 4", "status": "final", "teams": [{"name": "Juni Sjöland / Sofia Arvidsson", "players": [{"name": "Juni Sjöland", "country": "se"}, {"name": "Sofia Arvidsson", "country": "se"}]}, {"name": "Maja Åberg / Elma Misanovic", "players": [{"name": "Maja Åberg", "country": "se"}, {"name": "Elma Misanovic", "country": "se"}]}], "score": {"sets": [["6", "0"], ["6", "2"]], "winner": 0}}, {"className": "Dam A", "round": "Damer A", "court": "Bana 10", "status": "final", "teams": [{"name": "Cornelia Lister Haglind / Lisa Andersson", "players": [{"name": "Cornelia Lister Haglind", "country": "se"}, {"name": "Lisa Andersson", "country": "se"}]}, {"name": "Carla Barciela / Tea Hylander", "players": [{"name": "Carla Barciela", "country": "es"}, {"name": "Tea Hylander", "country": "se"}]}], "score": {"sets": [["6", "1"], ["6", "2"]], "winner": 0}}, {"className": "Dam A", "round": "Damer A", "court": "Bana 3", "status": "final", "teams": [{"name": "Baharak Soleymani / Maria García-Rasmussen", "players": [{"name": "Baharak Soleymani", "country": "se"}, {"name": "Maria García-Rasmussen", "country": "dk"}]}, {"name": "Eliza Bosson / Laura  Gomez", "players": [{"name": "Eliza Bosson", "country": "se"}, {"name": "Laura  Gomez", "country": "es"}]}], "score": {"sets": [], "winner": 0}}, {"className": "Herr B", "round": "Herrar B", "court": "Bana 2", "status": "final", "teams": [{"name": "Folke Rosén / Anton Johansson", "players": [{"name": "Folke Rosén", "country": "se"}, {"name": "Anton Johansson", "country": "se"}]}, {"name": "Noel Wändemark / Oskar Elmevik", "players": [{"name": "Noel Wändemark", "country": "se"}, {"name": "Oskar Elmevik", "country": "se"}]}], "score": {"sets": [["6", "3"], ["7", "6"]], "winner": 0}}, {"className": "Herr B", "round": "Herrar B", "court": "Bana 12", "status": "final", "teams": [{"name": "Malte Rasmusson / Hugo Henrysson", "players": [{"name": "Malte Rasmusson", "country": "se"}, {"name": "Hugo Henrysson", "country": "se"}]}, {"name": "Wiggo Johansson / Noak Halvardsson", "players": [{"name": "Wiggo Johansson", "country": "se"}, {"name": "Noak Halvardsson", "country": "se"}]}], "score": {"sets": [["6", "1"], ["6", "1"]], "winner": 0}}, {"className": "Herr B", "round": "Herrar B", "court": "Bana 11", "status": "final", "teams": [{"name": "Dannie Winther / Malte Lindh", "players": [{"name": "Dannie Winther", "country": "se"}, {"name": "Malte Lindh", "country": "se"}]}, {"name": "William Johansson / Alberto Gonzalez", "players": [{"name": "William Johansson", "country": "se"}, {"name": "Alberto Gonzalez", "country": "es"}]}], "score": {"sets": [["6", "2"], ["7", "5"]], "winner": 0}}, {"className": "Herr B", "round": "Herrar B", "court": "Bana 5", "status": "final", "teams": [{"name": "Pär zetterberg / Walter Rengensjö", "players": [{"name": "Pär zetterberg", "country": "se"}, {"name": "Walter Rengensjö", "country": "se"}]}, {"name": "Elliot Haväng / Linus Andersson", "players": [{"name": "Elliot Haväng", "country": "se"}, {"name": "Linus Andersson", "country": "se"}]}], "score": {"sets": [["6", "1"], ["6", "1"]], "winner": 0}}, {"className": "Herr C", "round": "Herrar C", "court": "Bana 16", "status": "final", "teams": [{"name": "Sixten Ahlquist / Waldemar Oddshammar", "players": [{"name": "Sixten Ahlquist", "country": "se"}, {"name": "Waldemar Oddshammar", "country": "se"}]}, {"name": "Magnus Wahlström / Jörgen Eriksson", "players": [{"name": "Magnus Wahlström", "country": "se"}, {"name": "Jörgen Eriksson", "country": "se"}]}], "score": {"sets": [["6", "2"], ["7", "5"]], "winner": 0}}, {"className": "Herr C", "round": "Herrar C", "court": "Bana 17", "status": "final", "teams": [{"name": "Claes Engström / Markus Hedin", "players": [{"name": "Claes Engström", "country": "se"}, {"name": "Markus Hedin", "country": "se"}]}, {"name": "Robin Dristig / Christopher Åberg", "players": [{"name": "Robin Dristig", "country": "se"}, {"name": "Christopher Åberg", "country": "se"}]}], "score": {"sets": [["6", "0"], ["6", "1"]], "winner": 0}}, {"className": "Herr C", "round": "Herrar C", "court": "Bana 14", "status": "final", "teams": [{"name": "Thomas Dalebring / Herman Nordin", "players": [{"name": "Thomas Dalebring", "country": "se"}, {"name": "Herman Nordin", "country": "se"}]}, {"name": "M. Faour / Oliver Ponné", "players": [{"name": "M. Faour", "country": "ps"}, {"name": "Oliver Ponné", "country": "se"}]}], "score": {"sets": [["3", "6"], ["6", "4"], ["1", "0"]], "winner": 0}}, {"className": "Herr C", "round": "Herrar C", "court": "Bana 13", "status": "final", "teams": [{"name": "Andreas Lindström / Jesper Andersson", "players": [{"name": "Andreas Lindström", "country": "se"}, {"name": "Jesper Andersson", "country": "se"}]}, {"name": "Alexander Olsson / Erik Andersson", "players": [{"name": "Alexander Olsson", "country": "se"}, {"name": "Erik Andersson", "country": "se"}]}], "score": {"sets": [["6", "1"], ["1", "6"], ["1", "0"]], "winner": 0}}, {"className": "Dam C", "round": "Damer C", "court": "Bana 15", "status": "final", "teams": [{"name": "Karin Thorbjörn / Niki Brantmark", "players": [{"name": "Karin Thorbjörn", "country": "se"}, {"name": "Niki Brantmark", "country": "se"}]}, {"name": "Therese Joelsson / Emelie Ljungberg", "players": [{"name": "Therese Joelsson", "country": "se"}, {"name": "Emelie Ljungberg", "country": "se"}]}], "score": {"sets": [["6", "4"], ["6", "2"]], "winner": 0}}, {"className": "Dam B", "round": "Damer B", "court": "Bana 1", "status": "final", "teams": [{"name": "Eva Berg / Birgitta Bengtson", "players": [{"name": "Eva Berg", "country": "se"}, {"name": "Birgitta Bengtson", "country": "se"}]}, {"name": "Emily Shabacker / Sophia Hagwell", "players": [{"name": "Emily Shabacker", "country": "se"}, {"name": "Sophia Hagwell", "country": "se"}]}], "score": {"sets": [], "winner": null}}, {"className": "Dam B", "round": "Damer B", "court": "Bana 2", "status": "final", "teams": [{"name": "Johanna Ejdelind / Caroline Molander", "players": [{"name": "Johanna Ejdelind", "country": "se"}, {"name": "Caroline Molander", "country": "se"}]}, {"name": "Ann-Charlotte Granqvist / Ulrika de Paulis", "players": [{"name": "Ann-Charlotte Granqvist", "country": "se"}, {"name": "Ulrika de Paulis", "country": "se"}]}], "score": {"sets": [], "winner": 0}}, {"className": "Mixed", "round": "Mixed", "court": "Bana 15", "status": "final", "teams": [{"name": "Linnéa Skymberg / Adam Gustafsson", "players": [{"name": "Linnéa Skymberg", "country": "se"}, {"name": "Adam Gustafsson", "country": "se"}]}, {"name": "Ellen Sassler / Alberto Gonzalez", "players": [{"name": "Ellen Sassler", "country": "se"}, {"name": "Alberto Gonzalez", "country": "es"}]}], "score": {"sets": [["6", "0"], ["6", "3"]], "winner": 0}}, {"className": "Mixed", "round": "Mixed", "court": "Bana 12", "status": "final", "teams": [{"name": "Greta Åberg / Elliot Haväng", "players": [{"name": "Greta Åberg", "country": "se"}, {"name": "Elliot Haväng", "country": "se"}]}, {"name": "Alexandra Lenz / Zebastian Jönsson", "players": [{"name": "Alexandra Lenz", "country": "se"}, {"name": "Zebastian Jönsson", "country": "se"}]}], "score": {"sets": [["6", "3"], ["6", "1"]], "winner": 0}}, {"className": "Öppen Herrklass osanktionerad", "round": "Öppen klass (osanktionerad)", "court": "Bana 17", "status": "final", "teams": [{"name": "Per  Nilsson / Jonas Borgh", "players": [{"name": "Per  Nilsson", "country": "rin"}, {"name": "Jonas Borgh", "country": "rin"}]}, {"name": "Håkan  Liljekvist / Jesper  Hellmark", "players": [{"name": "Håkan  Liljekvist", "country": "rin"}, {"name": "Jesper  Hellmark", "country": "rin"}]}], "score": {"sets": [["6", "4"], ["6", "4"]], "winner": 0}}, {"className": "Herr A", "round": "Herrar A", "court": "Bana 6 (centercourt)", "status": "final", "teams": [{"name": "Simon Yitbarek / Adam Axelsson", "players": [{"name": "Simon Yitbarek", "country": "se"}, {"name": "Adam Axelsson", "country": "se"}]}, {"name": "Adam Svensson / Marcus Månsson", "players": [{"name": "Adam Svensson", "country": "se"}, {"name": "Marcus Månsson", "country": "se"}]}], "score": {"sets": [["6", "1"], ["6", "2"]], "winner": 0}}, {"className": "Herr A", "round": "Herrar A", "court": "Bana 10", "status": "final", "teams": [{"name": "Daniel Appelgren / Linus Frost", "players": [{"name": "Daniel Appelgren", "country": "se"}, {"name": "Linus Frost", "country": "se"}]}, {"name": "Carl Knutsson / Oskar Govik", "players": [{"name": "Carl Knutsson", "country": "se"}, {"name": "Oskar Govik", "country": "se"}]}], "score": {"sets": [["6", "3"], ["6", "2"]], "winner": 0}}, {"className": "Herr C", "round": "Herrar C", "court": "Bana 11", "status": "final", "teams": [{"name": "Markus Ekstrand / Simon Lindell", "players": [{"name": "Markus Ekstrand", "country": "se"}, {"name": "Simon Lindell", "country": "se"}]}, {"name": "Tobias Sjölin / Rikard Brogårde", "players": [{"name": "Tobias Sjölin", "country": "se"}, {"name": "Rikard Brogårde", "country": "se"}]}], "score": {"sets": [], "winner": 0}}, {"className": "Dam C", "round": "Damer C", "court": "Bana 3", "status": "final", "teams": [{"name": "Tilda Mahrberg / Maja Jansson", "players": [{"name": "Tilda Mahrberg", "country": "se"}, {"name": "Maja Jansson", "country": "se"}]}, {"name": "Malin Jungåker / Ebba Jolde", "players": [{"name": "Malin Jungåker", "country": "se"}, {"name": "Ebba Jolde", "country": "se"}]}], "score": {"sets": [["6", "4"], ["6", "3"]], "winner": 0}}, {"className": "Dam C", "round": "Damer C", "court": "Bana 16", "status": "final", "teams": [{"name": "Malin Axelsson / Frida Glimstål", "players": [{"name": "Malin Axelsson", "country": "se"}, {"name": "Frida Glimstål", "country": "se"}]}, {"name": "Tina Johansson / Emma Mauritzon", "players": [{"name": "Tina Johansson", "country": "se"}, {"name": "Emma Mauritzon", "country": "se"}]}], "score": {"sets": [["6", "0"], ["7", "6"]], "winner": 0}}, {"className": "Dam C", "round": "Damer C", "court": "Bana 4", "status": "final", "teams": [{"name": "Evelina Norell / Jessica Andersson", "players": [{"name": "Evelina Norell", "country": "se"}, {"name": "Jessica Andersson", "country": "se"}]}, {"name": "Heli Hämäläinen / Caroline Blomsten", "players": [{"name": "Heli Hämäläinen", "country": "se"}, {"name": "Caroline Blomsten", "country": "se"}]}], "score": {"sets": [["6", "3"], ["6", "4"]], "winner": 0}}, {"className": "Dam C", "round": "Damer C", "court": "Bana 13", "status": "final", "teams": [{"name": "Mikaela Åkerman / Linnéa Freiding", "players": [{"name": "Mikaela Åkerman", "country": "se"}, {"name": "Linnéa Freiding", "country": "se"}]}, {"name": "Louise Malmström / Sofie Linderholm", "players": [{"name": "Louise Malmström", "country": "se"}, {"name": "Sofie Linderholm", "country": "se"}]}], "score": {"sets": [["6", "2"], ["6", "3"]], "winner": 0}}, {"className": "Dam A", "round": "Damer A", "court": "Bana 15", "status": "final", "teams": [{"name": "Elsa Blom / Emma Lindberg", "players": [{"name": "Elsa Blom", "country": "se"}, {"name": "Emma Lindberg", "country": "se"}]}, {"name": "Asta Renemark / Julia Gustafsson", "players": [{"name": "Asta Renemark", "country": "se"}, {"name": "Julia Gustafsson", "country": "se"}]}], "score": {"sets": [["6", "2"], ["6", "0"]], "winner": 0}}, {"className": "Dam B", "round": "Damer B", "court": "Bana 2", "status": "final", "teams": [{"name": "Jonna Opitz / Anna-Karin Svensson", "players": [{"name": "Jonna Opitz", "country": "se"}, {"name": "Anna-Karin Svensson", "country": "se"}]}, {"name": "Frida Bengtsson / Linda Mernsten", "players": [{"name": "Frida Bengtsson", "country": "se"}, {"name": "Linda Mernsten", "country": "se"}]}], "score": {"sets": [["7", "5"], ["7", "5"]], "winner": 0}}, {"className": "Dam B", "round": "Damer B", "court": "Bana 1", "status": "final", "teams": [{"name": "Selma Killman / Ann Roslund", "players": [{"name": "Selma Killman", "country": "se"}, {"name": "Ann Roslund", "country": "se"}]}, {"name": "Greta Åberg / Emilia Andreadis", "players": [{"name": "Greta Åberg", "country": "se"}, {"name": "Emilia Andreadis", "country": "se"}]}], "score": {"sets": [["6", "1"], ["6", "1"]], "winner": 0}}, {"className": "Mixed", "round": "Mixed", "court": "Bana 17", "status": "final", "teams": [{"name": "Ellen Sassler / Alberto Gonzalez", "players": [{"name": "Ellen Sassler", "country": "se"}, {"name": "Alberto Gonzalez", "country": "es"}]}, {"name": "Alexandra Lenz / Zebastian Jönsson", "players": [{"name": "Alexandra Lenz", "country": "se"}, {"name": "Zebastian Jönsson", "country": "se"}]}], "score": {"sets": [["6", "3"], ["6", "2"]], "winner": 0}}, {"className": "Herr A", "round": "Herrar A", "court": "Bana 4", "status": "final", "teams": [{"name": "Mac Grossmann / Adam Gustafsson", "players": [{"name": "Mac Grossmann", "country": "sk"}, {"name": "Adam Gustafsson", "country": "se"}]}, {"name": "Malte Badersten / Juan Figueroa Ayala", "players": [{"name": "Malte Badersten", "country": "se"}, {"name": "Juan Figueroa Ayala", "country": "es"}]}], "score": {"sets": [], "winner": 0}}, {"className": "Herr A", "round": "Herrar A", "court": "Bana 5", "status": "final", "teams": [{"name": "Emil Lilleøre / Nicolai Tranberg Ferrigno", "players": [{"name": "Emil Lilleøre", "country": "dk"}, {"name": "Nicolai Tranberg Ferrigno", "country": "dk"}]}, {"name": "Gustav Eriksson / Christoffer Persson", "players": [{"name": "Gustav Eriksson", "country": "se"}, {"name": "Christoffer Persson", "country": "se"}]}], "score": {"sets": [["7", "6"], ["7", "6"]], "winner": 0}}, {"className": "Herr A", "round": "Herrar A", "court": "Bana 6 (centercourt)", "status": "final", "teams": [{"name": "Albin Olsson / Douglas Rutgersson", "players": [{"name": "Albin Olsson", "country": "se"}, {"name": "Douglas Rutgersson", "country": "se"}]}, {"name": "Måns Stapel / Anton Mickelsson", "players": [{"name": "Måns Stapel", "country": "se"}, {"name": "Anton Mickelsson", "country": "se"}]}], "score": {"sets": [["6", "1"], ["6", "3"]], "winner": 0}}, {"className": "Herr A", "round": "Herrar A", "court": "Bana 10", "status": "final", "teams": [{"name": "Oscar Sebber / Alex Loughlan", "players": [{"name": "Oscar Sebber", "country": "dk"}, {"name": "Alex Loughlan", "country": "gb"}]}, {"name": "Ebbe Badersten / Pablo Sanchez Vicente", "players": [{"name": "Ebbe Badersten", "country": "se"}, {"name": "Pablo Sanchez Vicente", "country": "es"}]}], "score": {"sets": [["6", "1"], ["6", "1"]], "winner": 0}}, {"className": "Herr B", "round": "Herrar B", "court": "Bana 3", "status": "final", "teams": [{"name": "Folke Rosén / Anton Johansson", "players": [{"name": "Folke Rosén", "country": "se"}, {"name": "Anton Johansson", "country": "se"}]}, {"name": "Malte Rasmusson / Hugo Henrysson", "players": [{"name": "Malte Rasmusson", "country": "se"}, {"name": "Hugo Henrysson", "country": "se"}]}], "score": {"sets": [["6", "4"], ["7", "6"]], "winner": 0}}, {"className": "Herr B", "round": "Herrar B", "court": "Bana 11", "status": "final", "teams": [{"name": "Dannie Winther / Malte Lindh", "players": [{"name": "Dannie Winther", "country": "se"}, {"name": "Malte Lindh", "country": "se"}]}, {"name": "Pär zetterberg / Walter Rengensjö", "players": [{"name": "Pär zetterberg", "country": "se"}, {"name": "Walter Rengensjö", "country": "se"}]}], "score": {"sets": [["3", "6"], ["7", "5"], ["6", "3"]], "winner": 0}}, {"className": "Herr B", "round": "Herrar B", "court": "Bana 12", "status": "final", "teams": [{"name": "Anders Erikson / Anton Wittgren", "players": [{"name": "Anders Erikson", "country": "se"}, {"name": "Anton Wittgren", "country": "se"}]}, {"name": "Kristoffer Mohell Manneh / Jeronimo R Lacno", "players": [{"name": "Kristoffer Mohell Manneh", "country": "gm"}, {"name": "Jeronimo R Lacno", "country": "ph"}]}], "score": {"sets": [["6", "1"], ["6", "4"]], "winner": 0}}, {"className": "Herr C", "round": "Herrar C", "court": "Bana 16", "status": "final", "teams": [{"name": "Felix Erlanson / Ronny Norell", "players": [{"name": "Felix Erlanson", "country": "se"}, {"name": "Ronny Norell", "country": "se"}]}, {"name": "Markus Ekstrand / Simon Lindell", "players": [{"name": "Markus Ekstrand", "country": "se"}, {"name": "Simon Lindell", "country": "se"}]}], "score": {"sets": [["4", "6"], ["6", "4"], ["1", "0"]], "winner": 0}}, {"className": "Dam C", "round": "Damer C", "court": "Bana 13", "status": "final", "teams": [{"name": "Angela Dron / Cecilia Cederek", "players": [{"name": "Angela Dron", "country": "au"}, {"name": "Cecilia Cederek", "country": "se"}]}, {"name": "Therese Joelsson / Emelie Ljungberg", "players": [{"name": "Therese Joelsson", "country": "se"}, {"name": "Emelie Ljungberg", "country": "se"}]}], "score": {"sets": [], "winner": 0}}, {"className": "Dam B", "round": "Damer B", "court": "Bana 2", "status": "final", "teams": [{"name": "Johanna Ejdelind / Caroline Molander", "players": [{"name": "Johanna Ejdelind", "country": "se"}, {"name": "Caroline Molander", "country": "se"}]}, {"name": "Eva Berg / Birgitta Bengtson", "players": [{"name": "Eva Berg", "country": "se"}, {"name": "Birgitta Bengtson", "country": "se"}]}], "score": {"sets": [], "winner": 0}}, {"className": "Mixed", "round": "Mixed", "court": "Bana 14", "status": "final", "teams": [{"name": "Greta Åberg / Elliot Haväng", "players": [{"name": "Greta Åberg", "country": "se"}, {"name": "Elliot Haväng", "country": "se"}]}, {"name": "Moltas Råvik / Asta Renemark", "players": [{"name": "Moltas Råvik", "country": "se"}, {"name": "Asta Renemark", "country": "se"}]}], "score": {"sets": [["6", "7"], ["7", "5"], ["1", "0"]], "winner": 0}}, {"className": "Mixed", "round": "Mixed", "court": "Bana 16", "status": "final", "teams": [{"name": "Linnéa Skymberg / Adam Gustafsson", "players": [{"name": "Linnéa Skymberg", "country": "se"}, {"name": "Adam Gustafsson", "country": "se"}]}, {"name": "Alexandra Lenz / Zebastian Jönsson", "players": [{"name": "Alexandra Lenz", "country": "se"}, {"name": "Zebastian Jönsson", "country": "se"}]}], "score": {"sets": [["6", "1"], ["6", "1"]], "winner": 0}}, {"className": "Herr A", "round": "Herrar A", "court": "Bana 4", "status": "final", "teams": [{"name": "Mac Grossmann / Adam Gustafsson", "players": [{"name": "Mac Grossmann", "country": "sk"}, {"name": "Adam Gustafsson", "country": "se"}]}, {"name": "Oliver Hodos / Felix Bengtsson", "players": [{"name": "Oliver Hodos", "country": "se"}, {"name": "Felix Bengtsson", "country": "se"}]}], "score": {"sets": [], "winner": 0}}, {"className": "Herr C", "round": "Herrar C", "court": "Bana 12", "status": "final", "teams": [{"name": "Tim Apell / Kevin Long", "players": [{"name": "Tim Apell", "country": "se"}, {"name": "Kevin Long", "country": "se"}]}, {"name": "Daniel Eliasson / Oliver Parsons", "players": [{"name": "Daniel Eliasson", "country": "se"}, {"name": "Oliver Parsons", "country": "se"}]}], "score": {"sets": [["7", "5"], ["6", "4"]], "winner": 0}}, {"className": "Dam C", "round": "Damer C", "court": "Bana 5", "status": "final", "teams": [{"name": "Evelina Norell / Jessica Andersson", "players": [{"name": "Evelina Norell", "country": "se"}, {"name": "Jessica Andersson", "country": "se"}]}, {"name": "Malin Axelsson / Frida Glimstål", "players": [{"name": "Malin Axelsson", "country": "se"}, {"name": "Frida Glimstål", "country": "se"}]}], "score": {"sets": [["3", "6"], ["6", "1"], ["1", "0"]], "winner": 0}}, {"className": "Dam C", "round": "Damer C", "court": "Bana 11", "status": "final", "teams": [{"name": "Jaqueline Delang / Josefin Lindgren", "players": [{"name": "Jaqueline Delang", "country": "se"}, {"name": "Josefin Lindgren", "country": "se"}]}, {"name": "Karin Thorbjörn / Niki Brantmark", "players": [{"name": "Karin Thorbjörn", "country": "se"}, {"name": "Niki Brantmark", "country": "se"}]}], "score": {"sets": [["6", "3"], ["6", "2"]], "winner": 0}}, {"className": "Dam C", "round": "Damer C", "court": "Bana 3", "status": "final", "teams": [{"name": "Ewa Jönsson / Louise Falkengren", "players": [{"name": "Ewa Jönsson", "country": "se"}, {"name": "Louise Falkengren", "country": "se"}]}, {"name": "Stella Svensson / Ella Nordström", "players": [{"name": "Stella Svensson", "country": "se"}, {"name": "Ella Nordström", "country": "se"}]}], "score": {"sets": [["6", "3"], ["6", "4"]], "winner": 0}}, {"className": "Dam C", "round": "Damer C", "court": "Bana 1", "status": "final", "teams": [{"name": "Lola Teikari / Alice Andersson", "players": [{"name": "Lola Teikari", "country": "se"}, {"name": "Alice Andersson", "country": "se"}]}, {"name": "Mia Glimbrand / Sofia Grönvall", "players": [{"name": "Mia Glimbrand", "country": "se"}, {"name": "Sofia Grönvall", "country": "se"}]}], "score": {"sets": [["6", "1"], ["6", "4"]], "winner": 0}}, {"className": "Dam C", "round": "Damer C", "court": "Bana 13", "status": "final", "teams": [{"name": "Tilda Mahrberg / Maja Jansson", "players": [{"name": "Tilda Mahrberg", "country": "se"}, {"name": "Maja Jansson", "country": "se"}]}, {"name": "Angela Dron / Cecilia Cederek", "players": [{"name": "Angela Dron", "country": "au"}, {"name": "Cecilia Cederek", "country": "se"}]}], "score": {"sets": [["2", "6"], ["6", "4"], ["1", "0"]], "winner": 0}}, {"className": "Dam B", "round": "Damer B", "court": "Bana 10", "status": "final", "teams": [{"name": "Jonna Opitz / Anna-Karin Svensson", "players": [{"name": "Jonna Opitz", "country": "se"}, {"name": "Anna-Karin Svensson", "country": "se"}]}, {"name": "Selma Killman / Ann Roslund", "players": [{"name": "Selma Killman", "country": "se"}, {"name": "Ann Roslund", "country": "se"}]}], "score": {"sets": [["6", "2"], ["6", "4"]], "winner": 0}}, {"className": "Mixed", "round": "Mixed", "court": "Bana 11", "status": "final", "teams": [{"name": "Moltas Råvik / Asta Renemark", "players": [{"name": "Moltas Råvik", "country": "se"}, {"name": "Asta Renemark", "country": "se"}]}, {"name": "Alexandra Lenz / Zebastian Jönsson", "players": [{"name": "Alexandra Lenz", "country": "se"}, {"name": "Zebastian Jönsson", "country": "se"}]}], "score": {"sets": [["6", "2"], ["6", "2"]], "winner": 0}}, {"className": "Herr A", "round": "Herrar A", "court": "Bana 14", "status": "final", "teams": [{"name": "Gustav Eriksson / Christoffer Persson", "players": [{"name": "Gustav Eriksson", "country": "se"}, {"name": "Christoffer Persson", "country": "se"}]}, {"name": "Willy Tiger Släryd / Huysveld Isaac", "players": [{"name": "Willy Tiger Släryd", "country": "se"}, {"name": "Huysveld Isaac", "country": "be"}]}], "score": {"sets": [], "winner": null}}, {"className": "Herr A", "round": "Herrar A", "court": "Bana 16", "status": "final", "teams": [{"name": "Oliver Hodos / Felix Bengtsson", "players": [{"name": "Oliver Hodos", "country": "se"}, {"name": "Felix Bengtsson", "country": "se"}]}, {"name": "Alfons Lopez / Adam Ottosson", "players": [{"name": "Alfons Lopez", "country": "se"}, {"name": "Adam Ottosson", "country": "se"}]}], "score": {"sets": [], "winner": null}}, {"className": "Herr B", "round": "Herrar B", "court": "Bana 6 (centercourt)", "status": "final", "teams": [{"name": "Folke Rosén / Anton Johansson", "players": [{"name": "Folke Rosén", "country": "se"}, {"name": "Anton Johansson", "country": "se"}]}, {"name": "Dannie Winther / Malte Lindh", "players": [{"name": "Dannie Winther", "country": "se"}, {"name": "Malte Lindh", "country": "se"}]}], "score": {"sets": [["6", "3"], ["6", "2"]], "winner": 0}}, {"className": "Herr B", "round": "Herrar B", "court": "Bana 13", "status": "final", "teams": [{"name": "Kristoffer Mohell Manneh / Jeronimo R Lacno", "players": [{"name": "Kristoffer Mohell Manneh", "country": "gm"}, {"name": "Jeronimo R Lacno", "country": "ph"}]}, {"name": "Fredrik Ifvarsson / Fredrik Grundström", "players": [{"name": "Fredrik Ifvarsson", "country": "se"}, {"name": "Fredrik Grundström", "country": "se"}]}], "score": {"sets": [], "winner": null}}, {"className": "Herr A", "round": "Herrar A", "court": "Bana 6 (centercourt)", "status": "final", "teams": [{"name": "Emil Lilleøre / Nicolai Tranberg Ferrigno", "players": [{"name": "Emil Lilleøre", "country": "dk"}, {"name": "Nicolai Tranberg Ferrigno", "country": "dk"}]}, {"name": "Mac Grossmann / Adam Gustafsson", "players": [{"name": "Mac Grossmann", "country": "sk"}, {"name": "Adam Gustafsson", "country": "se"}]}], "score": {"sets": [], "winner": 0}}, {"className": "Dam A", "round": "Damer A", "court": "Bana 10", "status": "final", "teams": [{"name": "Juni Sjöland / Sofia Arvidsson", "players": [{"name": "Juni Sjöland", "country": "se"}, {"name": "Sofia Arvidsson", "country": "se"}]}, {"name": "Cornelia Lister Haglind / Lisa Andersson", "players": [{"name": "Cornelia Lister Haglind", "country": "se"}, {"name": "Lisa Andersson", "country": "se"}]}], "score": {"sets": [["7", "6"], ["3", "6"], ["7", "5"]], "winner": 0}}, {"className": "Dam A", "round": "Damer A", "court": "Bana 6 (centercourt)", "status": "final", "teams": [{"name": "Linnea Björk / Amanda Girdo", "players": [{"name": "Linnea Björk", "country": "se"}, {"name": "Amanda Girdo", "country": "se"}]}, {"name": "Baharak Soleymani / Maria García-Rasmussen", "players": [{"name": "Baharak Soleymani", "country": "se"}, {"name": "Maria García-Rasmussen", "country": "dk"}]}], "score": {"sets": [["6", "2"], ["6", "2"]], "winner": 0}}, {"className": "Dam A", "round": "Damer A", "court": "Bana 5", "status": "final", "teams": [{"name": "Ella Ho / Anna Riisgaard", "players": [{"name": "Ella Ho", "country": "se"}, {"name": "Anna Riisgaard", "country": "dk"}]}, {"name": "Elsa Blom / Emma Lindberg", "players": [{"name": "Elsa Blom", "country": "se"}, {"name": "Emma Lindberg", "country": "se"}]}], "score": {"sets": [], "winner": null}}, {"className": "Mixed", "round": "Mixed", "court": "Bana 2", "status": "final", "teams": [{"name": "Linnéa Skymberg / Adam Gustafsson", "players": [{"name": "Linnéa Skymberg", "country": "se"}, {"name": "Adam Gustafsson", "country": "se"}]}, {"name": "Moltas Råvik / Asta Renemark", "players": [{"name": "Moltas Råvik", "country": "se"}, {"name": "Asta Renemark", "country": "se"}]}], "score": {"sets": [["5", "7"], ["6", "1"], ["1", "0"]], "winner": 0}}, {"className": "Mixed", "round": "Mixed", "court": "Bana 12", "status": "final", "teams": [{"name": "Greta Åberg / Elliot Haväng", "players": [{"name": "Greta Åberg", "country": "se"}, {"name": "Elliot Haväng", "country": "se"}]}, {"name": "Ellen Sassler / Alberto Gonzalez", "players": [{"name": "Ellen Sassler", "country": "se"}, {"name": "Alberto Gonzalez", "country": "es"}]}], "score": {"sets": [["6", "3"], ["6", "7"], ["1", "0"]], "winner": 0}}, {"className": "Herr D", "round": "Herrar D", "court": "Bana 4", "status": "final", "teams": [{"name": "Robin Skoglund / Vlado Grossmann", "players": [{"name": "Robin Skoglund", "country": "se"}, {"name": "Vlado Grossmann", "country": "se"}]}, {"name": "Joel Lindberg / Oskar Jönsson", "players": [{"name": "Joel Lindberg", "country": "se"}, {"name": "Oskar Jönsson", "country": "se"}]}], "score": {"sets": [], "winner": null}}, {"className": "Herr D", "round": "Herrar D", "court": "Bana 15", "status": "final", "teams": [{"name": "Jimmie Gabrielsson / Liam Gabrielsson", "players": [{"name": "Jimmie Gabrielsson", "country": "se"}, {"name": "Liam Gabrielsson", "country": "se"}]}, {"name": "Dominiq Appelqvist / Sebastian Ferm", "players": [{"name": "Dominiq Appelqvist", "country": "se"}, {"name": "Sebastian Ferm", "country": "se"}]}], "score": {"sets": [["5", "7"], ["6", "2"], ["1", "0"]], "winner": 0}}, {"className": "Herr D", "round": "Herrar D", "court": "Bana 3", "status": "final", "teams": [{"name": "Fredrik Hagwell / Carl Hagwell", "players": [{"name": "Fredrik Hagwell", "country": "se"}, {"name": "Carl Hagwell", "country": "se"}]}, {"name": "Hampus Andersson / Oscar Ekström", "players": [{"name": "Hampus Andersson", "country": "se"}, {"name": "Oscar Ekström", "country": "se"}]}], "score": {"sets": [["6", "3"], ["6", "1"]], "winner": 0}}, {"className": "Herr A", "round": "Herrar A", "court": "Bana 10", "status": "final", "teams": [{"name": "Simon Yitbarek / Adam Axelsson", "players": [{"name": "Simon Yitbarek", "country": "se"}, {"name": "Adam Axelsson", "country": "se"}]}, {"name": "Daniel Appelgren / Linus Frost", "players": [{"name": "Daniel Appelgren", "country": "se"}, {"name": "Linus Frost", "country": "se"}]}], "score": {"sets": [["6", "3"], ["1", "6"], ["6", "3"]], "winner": 0}}, {"className": "Herr A", "round": "Herrar A", "court": "Bana 6 (centercourt)", "status": "final", "teams": [{"name": "Albin Olsson / Douglas Rutgersson", "players": [{"name": "Albin Olsson", "country": "se"}, {"name": "Douglas Rutgersson", "country": "se"}]}, {"name": "Oscar Sebber / Alex Loughlan", "players": [{"name": "Oscar Sebber", "country": "dk"}, {"name": "Alex Loughlan", "country": "gb"}]}], "score": {"sets": [["7", "6"], ["7", "6"]], "winner": 0}}, {"className": "Herr C", "round": "Herrar C", "court": "Bana 12", "status": "final", "teams": [{"name": "Sixten Ahlquist / Waldemar Oddshammar", "players": [{"name": "Sixten Ahlquist", "country": "se"}, {"name": "Waldemar Oddshammar", "country": "se"}]}, {"name": "Andreas Lindström / Jesper Andersson", "players": [{"name": "Andreas Lindström", "country": "se"}, {"name": "Jesper Andersson", "country": "se"}]}], "score": {"sets": [["3", "6"], ["6", "4"], ["6", "3"]], "winner": 0}}, {"className": "Herr C", "round": "Herrar C", "court": "Bana 13", "status": "final", "teams": [{"name": "Claes Engström / Markus Hedin", "players": [{"name": "Claes Engström", "country": "se"}, {"name": "Markus Hedin", "country": "se"}]}, {"name": "Thomas Dalebring / Herman Nordin", "players": [{"name": "Thomas Dalebring", "country": "se"}, {"name": "Herman Nordin", "country": "se"}]}], "score": {"sets": [["3", "6"], ["6", "4"], ["6", "2"]], "winner": 0}}, {"className": "Herr C", "round": "Herrar C", "court": "Bana 5", "status": "final", "teams": [{"name": "Felix Erlanson / Ronny Norell", "players": [{"name": "Felix Erlanson", "country": "se"}, {"name": "Ronny Norell", "country": "se"}]}, {"name": "Tim Apell / Kevin Long", "players": [{"name": "Tim Apell", "country": "se"}, {"name": "Kevin Long", "country": "se"}]}], "score": {"sets": [["2", "6"], ["7", "5"], ["1", "0"]], "winner": 0}}, {"className": "Herr D", "round": "Herrar D", "court": "Bana 1", "status": "final", "teams": [{"name": "Robin Skoglund / Vlado Grossmann", "players": [{"name": "Robin Skoglund", "country": "se"}, {"name": "Vlado Grossmann", "country": "se"}]}, {"name": "Jonas Dahlquist / Patric Nilsson", "players": [{"name": "Jonas Dahlquist", "country": "se"}, {"name": "Patric Nilsson", "country": "se"}]}], "score": {"sets": [["6", "3"], ["7", "6"]], "winner": 0}}, {"className": "Herr D", "round": "Herrar D", "court": "Bana 14", "status": "final", "teams": [{"name": "Rico Nadarevic / Eddi Migic", "players": [{"name": "Rico Nadarevic", "country": "se"}, {"name": "Eddi Migic", "country": "se"}]}, {"name": "Melvin Aronsson / Elias Larsson", "players": [{"name": "Melvin Aronsson", "country": "se"}, {"name": "Elias Larsson", "country": "se"}]}], "score": {"sets": [], "winner": null}}, {"className": "Herr D", "round": "Herrar D", "court": "Bana 2", "status": "final", "teams": [{"name": "Moltas Råvik / Vilgot Wallmark", "players": [{"name": "Moltas Råvik", "country": "se"}, {"name": "Vilgot Wallmark", "country": "se"}]}, {"name": "Johan Wester / Mattias Nilsson", "players": [{"name": "Johan Wester", "country": "se"}, {"name": "Mattias Nilsson", "country": "se"}]}], "score": {"sets": [], "winner": null}}, {"className": "Herr D", "round": "Herrar D", "court": "Bana 3", "status": "final", "teams": [{"name": "Melvin Aronsson / Elias Larsson", "players": [{"name": "Melvin Aronsson", "country": "se"}, {"name": "Elias Larsson", "country": "se"}]}, {"name": "Joel Lindberg / Oskar Jönsson", "players": [{"name": "Joel Lindberg", "country": "se"}, {"name": "Oskar Jönsson", "country": "se"}]}], "score": {"sets": [], "winner": null}}, {"className": "Mixed", "round": "Mixed", "court": "Bana 13", "status": "final", "teams": [{"name": "Linnéa Skymberg / Adam Gustafsson", "players": [{"name": "Linnéa Skymberg", "country": "se"}, {"name": "Adam Gustafsson", "country": "se"}]}, {"name": "Greta Åberg / Elliot Haväng", "players": [{"name": "Greta Åberg", "country": "se"}, {"name": "Elliot Haväng", "country": "se"}]}], "score": {"sets": [["6", "3"], ["6", "1"]], "winner": 0}}, {"className": "Dam C", "round": "Damer C", "court": "Bana 6 (centercourt)", "status": "final", "teams": [{"name": "Jaqueline Delang / Josefin Lindgren", "players": [{"name": "Jaqueline Delang", "country": "se"}, {"name": "Josefin Lindgren", "country": "se"}]}, {"name": "Mikaela Åkerman / Linnéa Freiding", "players": [{"name": "Mikaela Åkerman", "country": "se"}, {"name": "Linnéa Freiding", "country": "se"}]}], "score": {"sets": [["7", "5"], ["6", "4"]], "winner": 0}}, {"className": "Dam C", "round": "Damer C", "court": "Bana 5", "status": "final", "teams": [{"name": "Lola Teikari / Alice Andersson", "players": [{"name": "Lola Teikari", "country": "se"}, {"name": "Alice Andersson", "country": "se"}]}, {"name": "Ewa Jönsson / Louise Falkengren", "players": [{"name": "Ewa Jönsson", "country": "se"}, {"name": "Louise Falkengren", "country": "se"}]}], "score": {"sets": [], "winner": 0}}, {"className": "Dam C", "round": "Damer C", "court": "Bana 11", "status": "final", "teams": [{"name": "Tilda Mahrberg / Maja Jansson", "players": [{"name": "Tilda Mahrberg", "country": "se"}, {"name": "Maja Jansson", "country": "se"}]}, {"name": "Evelina Norell / Jessica Andersson", "players": [{"name": "Evelina Norell", "country": "se"}, {"name": "Jessica Andersson", "country": "se"}]}], "score": {"sets": [["7", "5"], ["4", "6"], ["1", "0"]], "winner": 0}}, {"className": "Herr D", "round": "Herrar D", "court": "Bana 14", "status": "final", "teams": [{"name": "Dominiq Appelqvist / Sebastian Ferm", "players": [{"name": "Dominiq Appelqvist", "country": "se"}, {"name": "Sebastian Ferm", "country": "se"}]}, {"name": "Hampus Andersson / Oscar Ekström", "players": [{"name": "Hampus Andersson", "country": "se"}, {"name": "Oscar Ekström", "country": "se"}]}], "score": {"sets": [["6", "2"], ["7", "6"]], "winner": 0}}, {"className": "Herr D", "round": "Herrar D", "court": "Bana 15", "status": "final", "teams": [{"name": "Dominiq Appelqvist / Sebastian Ferm", "players": [{"name": "Dominiq Appelqvist", "country": "se"}, {"name": "Sebastian Ferm", "country": "se"}]}, {"name": "Johan Wester / Mattias Nilsson", "players": [{"name": "Johan Wester", "country": "se"}, {"name": "Mattias Nilsson", "country": "se"}]}], "score": {"sets": [], "winner": null}}, {"className": "Herr D", "round": "Herrar D", "court": "Bana 1", "status": "final", "teams": [{"name": "Emil Westerlund / Rasmus Lindeberg", "players": [{"name": "Emil Westerlund", "country": "se"}, {"name": "Rasmus Lindeberg", "country": "se"}]}, {"name": "Rico Nadarevic / Eddi Migic", "players": [{"name": "Rico Nadarevic", "country": "se"}, {"name": "Eddi Migic", "country": "se"}]}], "score": {"sets": [["6", "0"], ["6", "0"]], "winner": 0}}, {"className": "Herr D", "round": "Herrar D", "court": "Bana 3", "status": "final", "teams": [{"name": "Moltas Råvik / Vilgot Wallmark", "players": [{"name": "Moltas Råvik", "country": "se"}, {"name": "Vilgot Wallmark", "country": "se"}]}, {"name": "Jimmie Gabrielsson / Liam Gabrielsson", "players": [{"name": "Jimmie Gabrielsson", "country": "se"}, {"name": "Liam Gabrielsson", "country": "se"}]}], "score": {"sets": [["7", "6"], ["6", "1"]], "winner": 0}}, {"className": "Herr D", "round": "Herrar D", "court": "Bana 2", "status": "final", "teams": [{"name": "Fredrik Hagwell / Carl Hagwell", "players": [{"name": "Fredrik Hagwell", "country": "se"}, {"name": "Carl Hagwell", "country": "se"}]}, {"name": "Vincent MacDonald / Andreas MacDonald", "players": [{"name": "Vincent MacDonald", "country": "se"}, {"name": "Andreas MacDonald", "country": "se"}]}], "score": {"sets": [["6", "1"], ["6", "4"]], "winner": 0}}, {"className": "Mixed", "round": "Mixed", "court": "Bana 13", "status": "final", "teams": [{"name": "Moltas Råvik / Asta Renemark", "players": [{"name": "Moltas Råvik", "country": "se"}, {"name": "Asta Renemark", "country": "se"}]}, {"name": "Ellen Sassler / Alberto Gonzalez", "players": [{"name": "Ellen Sassler", "country": "se"}, {"name": "Alberto Gonzalez", "country": "es"}]}], "score": {"sets": [], "winner": 0}}, {"className": "Herr D", "round": "Herrar D", "court": "Bana 11", "status": "final", "teams": [{"name": "Robin Skoglund / Vlado Grossmann", "players": [{"name": "Robin Skoglund", "country": "se"}, {"name": "Vlado Grossmann", "country": "se"}]}, {"name": "Emil Westerlund / Rasmus Lindeberg", "players": [{"name": "Emil Westerlund", "country": "se"}, {"name": "Rasmus Lindeberg", "country": "se"}]}], "score": {"sets": [["6", "4"], ["6", "1"]], "winner": 0}}, {"className": "Dam A", "round": "Damer A", "court": "Bana 6 (centercourt)", "status": "final", "teams": [{"name": "Linnea Björk / Amanda Girdo", "players": [{"name": "Linnea Björk", "country": "se"}, {"name": "Amanda Girdo", "country": "se"}]}, {"name": "Juni Sjöland / Sofia Arvidsson", "players": [{"name": "Juni Sjöland", "country": "se"}, {"name": "Sofia Arvidsson", "country": "se"}]}], "score": {"sets": [["6", "4"], ["6", "3"]], "winner": 0}}, {"className": "Herr C", "round": "Herrar C", "court": "Bana 10", "status": "final", "teams": [{"name": "Claes Engström / Markus Hedin", "players": [{"name": "Claes Engström", "country": "se"}, {"name": "Markus Hedin", "country": "se"}]}, {"name": "Sixten Ahlquist / Waldemar Oddshammar", "players": [{"name": "Sixten Ahlquist", "country": "se"}, {"name": "Waldemar Oddshammar", "country": "se"}]}], "score": {"sets": [["6", "4"], ["7", "5"]], "winner": 0}}, {"className": "Dam C", "round": "Damer C", "court": "Bana 11", "status": "final", "teams": [{"name": "Jaqueline Delang / Josefin Lindgren", "players": [{"name": "Jaqueline Delang", "country": "se"}, {"name": "Josefin Lindgren", "country": "se"}]}, {"name": "Lola Teikari / Alice Andersson", "players": [{"name": "Lola Teikari", "country": "se"}, {"name": "Alice Andersson", "country": "se"}]}], "score": {"sets": [["6", "2"], ["6", "2"]], "winner": 0}}, {"className": "Herr D", "round": "Herrar D", "court": "Bana 12", "status": "final", "teams": [{"name": "Fredrik Hagwell / Carl Hagwell", "players": [{"name": "Fredrik Hagwell", "country": "se"}, {"name": "Carl Hagwell", "country": "se"}]}, {"name": "Moltas Råvik / Vilgot Wallmark", "players": [{"name": "Moltas Råvik", "country": "se"}, {"name": "Vilgot Wallmark", "country": "se"}]}], "score": {"sets": [["7", "5"], ["6", "3"]], "winner": 0}}, {"className": "Herr A", "round": "Herrar A", "court": "Bana 6 (centercourt)", "status": "final", "teams": [{"name": "Albin Olsson / Douglas Rutgersson", "players": [{"name": "Albin Olsson", "country": "se"}, {"name": "Douglas Rutgersson", "country": "se"}]}, {"name": "Simon Yitbarek / Adam Axelsson", "players": [{"name": "Simon Yitbarek", "country": "se"}, {"name": "Adam Axelsson", "country": "se"}]}], "score": {"sets": [["2", "6"], ["6", "4"], ["6", "4"]], "winner": 0}}, {"className": "Herr D", "round": "Herrar D", "court": "Bana 6 (centercourt)", "status": "final", "teams": [{"name": "Robin Skoglund / Vlado Grossmann", "players": [{"name": "Robin Skoglund", "country": "se"}, {"name": "Vlado Grossmann", "country": "se"}]}, {"name": "Fredrik Hagwell / Carl Hagwell", "players": [{"name": "Fredrik Hagwell", "country": "se"}, {"name": "Carl Hagwell", "country": "se"}]}], "score": {"sets": [["7", "6"], ["1", "6"], ["6", "1"]], "winner": 0}}, {"className": "Herr D", "round": "Herrar D", "court": "Bana 10", "status": "final", "teams": [{"name": "Dominiq Appelqvist / Sebastian Ferm", "players": [{"name": "Dominiq Appelqvist", "country": "se"}, {"name": "Sebastian Ferm", "country": "se"}]}, {"name": "Melvin Aronsson / Elias Larsson", "players": [{"name": "Melvin Aronsson", "country": "se"}, {"name": "Elias Larsson", "country": "se"}]}], "score": {"sets": [], "winner": null}}]}